idoji.py
idoji-1.0.1.dist-info/LICENSE
idoji-1.0.1.dist-info/METADATA
idoji-1.0.1.dist-info/WHEEL
idoji-1.0.1.dist-info/entry_points.txt
idoji-1.0.1.dist-info/top_level.txt
idoji-1.0.1.dist-info/RECORD
