Metadata-Version: 2.1
Name: idoji
Version: 1.0.1
Summary: Generate unique identifiers only using emojis
Home-page: https://github.com/SteveCharleston/idoji
Author: SteveCharleston
Author-email: steven@schalhorn.org
License: GPLv3
Project-URL: Bug Tracker, https://github.com/SteveCharleston/idoji/issues
Platform: UNKNOWN
Classifier: Programming Language :: Python
Classifier: Programming Language :: Python :: 3
Classifier: Programming Language :: Python :: 3.6
Classifier: Programming Language :: Python :: 3.7
Classifier: Programming Language :: Python :: 3.8
Classifier: Programming Language :: Python :: 3.9
Classifier: Programming Language :: Python :: 3.10
Classifier: License :: OSI Approved :: GNU General Public License v3 (GPLv3)
Classifier: Operating System :: OS Independent
Classifier: Intended Audience :: Developers
Classifier: Topic :: Software Development :: Libraries :: Python Modules
Requires-Python: >=3.6
